Martinoid/Martinoid2.py
Martinoid/__init__.py
Martinoid/__main__.py
Martinoid/_martinoid_data.py
Martinoid/version.py
Martinoid/Data/Na.csv
Martinoid/Data/Nab.csv
Martinoid/Data/Nd.csv
Martinoid/Data/Ne.csv
Martinoid/Data/Nf.csv
Martinoid/Data/Nfe.csv
Martinoid/Data/NfeB4.csv
Martinoid/Data/NfeC4.csv
Martinoid/Data/Nfex.csv
Martinoid/Data/Nfn.csv
Martinoid/Data/Nfnap.csv
Martinoid/Data/Ni.csv
Martinoid/Data/Nk.csv
Martinoid/Data/Nke.csv
Martinoid/Data/Nkeqm.csv
Martinoid/Data/Nl.csv
Martinoid/Data/Nm.csv
Martinoid/Data/NmO.csv
Martinoid/Data/Nn.csv
Martinoid/Data/Nq.csv
Martinoid/Data/Nr.csv
Martinoid/Data/Ns.csv
Martinoid/Data/Nse.csv
Martinoid/Data/Nt.csv
Martinoid/Data/Nv.csv
Martinoid/Data/Nw.csv
Martinoid/Data/Nwe.csv
Martinoid/Data/Ny.csv
Martinoid-0.1.0.dist-info/METADATA
Martinoid-0.1.0.dist-info/WHEEL
Martinoid-0.1.0.dist-info/top_level.txt
Martinoid-0.1.0.dist-info/RECORD
