Metadata-Version: 2.1
Name: Martinoid
Version: 0.1.0
Summary: This module was inspired by martinize (http://cgmartini.nl/index.php/tools2/proteins-and-bilayers/204-martinize) and has been created to perform automatic topology building of peptoids within the MARTINI forcefield (v2.1) in the GROMACS program.
Home-page: https://github.com/Hamish-cmyk/MartinoidPeptoidCG
Author: Hamish W. A. Swanson, Alexander van Teijlingen
Author-email: a.vant@linuxmail.org
License: BSD 2-clause
Classifier: Intended Audience :: Science/Research
Classifier: Programming Language :: Python :: 3.10
Requires-Dist: ase
Requires-Dist: pandas
Requires-Dist: numpy
Requires-Dist: mdtraj
Requires-Dist: matplotlib
Requires-Dist: argparse
